{"errors":[],"warnings":[],"namedChunkGroups":{"app":{"chunks":[5,0,4,1],"assets":["webpack-runtime-060c859bf834d16d23c4.js","webpack-runtime-060c859bf834d16d23c4.js.map","styles.22ed0a1dea5253a3dddd.css","styles.22ed0a1dea5253a3dddd.css","styles-9b6f388623a2ec93d35f.js","styles-9b6f388623a2ec93d35f.js.map","framework-16534ddc5a576711dd15.js","framework-16534ddc5a576711dd15.js.map","app-fb91ee20fcb6867a8910.js","app-fb91ee20fcb6867a8910.js.map"],"children":{},"childAssets":{}},"component---src-pages-404-tsx":{"chunks":[2],"assets":["component---src-pages-404-tsx-bb98f2ff7ea136b22024.js","component---src-pages-404-tsx-bb98f2ff7ea136b22024.js.map"],"children":{},"childAssets":{}},"component---src-pages-index-tsx":{"chunks":[0,3],"assets":["styles.22ed0a1dea5253a3dddd.css","styles.22ed0a1dea5253a3dddd.css","styles-9b6f388623a2ec93d35f.js","styles-9b6f388623a2ec93d35f.js.map","component---src-pages-index-tsx-e66ce0f603b2b021e58f.js","component---src-pages-index-tsx-e66ce0f603b2b021e58f.js.map"],"children":{},"childAssets":{}}},"assetsByChunkName":{"app":["webpack-runtime-060c859bf834d16d23c4.js","styles.22ed0a1dea5253a3dddd.css","styles.22ed0a1dea5253a3dddd.css","styles-9b6f388623a2ec93d35f.js","framework-16534ddc5a576711dd15.js","app-fb91ee20fcb6867a8910.js"],"component---src-pages-404-tsx":["component---src-pages-404-tsx-bb98f2ff7ea136b22024.js"],"component---src-pages-index-tsx":["styles.22ed0a1dea5253a3dddd.css","styles.22ed0a1dea5253a3dddd.css","styles-9b6f388623a2ec93d35f.js","component---src-pages-index-tsx-e66ce0f603b2b021e58f.js"]}}